pypresseportal/__init__.py
pypresseportal/constants.py
pypresseportal/pypresseportal.py
pypresseportal/pypresseportal_constants.py
pypresseportal/pypresseportal_errors.py
pypresseportal-0.1.dist-info/LICENSE
pypresseportal-0.1.dist-info/METADATA
pypresseportal-0.1.dist-info/WHEEL
pypresseportal-0.1.dist-info/top_level.txt
pypresseportal-0.1.dist-info/RECORD
