Metadata-Version: 2.1
Name: pypresseportal
Version: 0.1
Summary: Python wrapper for the presseportal.de API
Home-page: https://github.com/tcmetzger/pypresseportal
Author: Timo Cornelius Metzger
Author-email: coding@tcmetzger.net
License: MIT
Keywords: pypresseportal,presseportal,DPA,press release,press releases,police,fire department,news,journalism,Germany
Platform: UNKNOWN
Classifier: Development Status :: 3 - Alpha
Classifier: Programming Language :: Python :: 3
Classifier: License :: OSI Approved :: MIT License
Classifier: Natural Language :: English
Classifier: Operating System :: OS Independent
Requires-Python: >=3.6
Requires-Dist: requests
